ua_parse/__init__.py
ua_parse/constants.py
ua_parse/helpers.py
ua_parse/lib.py
ua_parse/regexes.py
ua_parse-1.0.1.dist-info/METADATA
ua_parse-1.0.1.dist-info/WHEEL
ua_parse-1.0.1.dist-info/top_level.txt
ua_parse-1.0.1.dist-info/RECORD
